{
  "slug": "freestylefly-412",
  "title": "这条 prompt 通过详细描述了一个高级、专业且具有未来感的城市地铁系统的视觉呈现，非常适合用于展示前沿技术和设计细节，适合应用于高科技产品发布会、城市规划展览或高端建筑设计杂志等中文营销场景。",
  "scene": "cross-border",
  "industry": "other",
  "style": "minimal",
  "image_url": "/assets/freestylefly-412/v1.webp",
  "image_alt": "这条 prompt 通过详细描述了一个高级、专业且具有未来感的城市地铁系统的视觉呈现，非常适合用于展示前沿技术和设计细节，适合应用于高科技产品发布会、城市规划展览或高端建筑设计杂志等中文营销场景。",
  "prompt_original": "Create a premium square “reference-style urban transportation infographic” centered around a futuristic modern metro system called the {METRO_NAME}, designed as a beautifully curated transit-engineering handbook page rather than a public transport advertisement.\n\nThe composition should feel like a modern visual encyclopedia mixed with an elite railway infrastructure field guide and high-end editorial infographic system.\n\nVisual Direction:\n\n• 1:1 square composition\n• Dark premium urban-tech background with subtle railway schematics, metro maps, and futuristic blueprint overlays\n• Elegant palette using deep navy, matte black, steel gray, electric blue accents, and soft white lighting\n• Refined editorial typography hierarchy with modern transportation aesthetics\n• Rounded modular information cards with clean spacing\n• Gentle realistic reflections and premium HUD-style dividers\n• Minimal transit-system iconography\n• Extremely detailed central metro train render viewed in dramatic three-quarter perspective inside a futuristic underground station\n• Thin precision annotation lines pointing toward transportation systems and smart engineering features\n• Clean, organized “knowledge-first” layout with high information density but breathable spacing\n\nMain Subject Presentation:\n\nA stunning ultra-detailed realistic render of the {METRO_NAME} modern metro train placed at the center, featuring sleek aerodynamic train design, glowing destination displays, realistic stainless-steel textures, illuminated station lighting, smart glass windows, premium urban-environment realism, and futuristic rail infrastructure.\n\nSurround the metro with scientific and engineering callouts explaining:\n\n• regenerative braking system\n• smart signalling & CBTC control\n• electric propulsion system\n• passenger information systems\n• safety and surveillance technology\n• platform screen doors\n• energy-efficient design\n• smart ventilation systems\n• accessibility features\n• track and infrastructure engineering\n\nInclude modular infographic sections such as:\n\n• Metro System Overview\n• Technical Specifications\n• Train Dimensions & Layout\n• Passenger Capacity & Flow\n• Smart Control Systems\n• Sustainability Features\n• Track & Infrastructure Engineering\n• Signalling & Automation\n• Station Design & Facilities\n• Safety & Emergency Systems\n• Passenger Experience Features\n• Urban Connectivity & Network Map\n• Energy Efficiency Comparison\n• Construction & Expansion Timeline\n• “Top 5 Smart Innovations” section\n• Built for Future Smart Cities\n\nAdd small premium visualization modules like:\n\n• metro network maps\n• train blueprint diagrams\n• station layout graphics\n• passenger flow visualizations\n• signalling workflow diagrams\n• energy-efficiency comparison charts\n• train configuration illustrations\n• smart-city connectivity graphics\n• platform safety diagrams\n• infrastructure cross-section visuals\n\nStyle Keywords:\n\n“premium urban mobility encyclopedia”\n“editorial metro engineering handbook”\n“high-end transportation infographic”\n“scientific railway infrastructure poster”\n“museum-quality transit reference page”\n“modular smart-city knowledge system”\n“clean transportation editorial design”\n“ultra-detailed metro visualization”\n\nAvoid:\n\n• cluttered public advertisement aesthetics\n• cartoon transportation styling\n• unrealistic sci-fi levitating trains\n• excessive cyberpunk neon overload\n• chaotic city scenes\n• generic subway poster layouts\n\nThe final result should resemble a professionally published railway infrastructure reference-book page created for transit enthusiasts, architects, engineers, urban planners, transportation designers, and educational infrastructure archives.",
  "prompt_zh": "创建一个高级方形的“参考风格城市交通信息图”，围绕一个名为{METRO_NAME}的未来现代地铁系统设计，将其设计成一个精美的交通工程手册页面，而不是公共交通广告。构图应感觉像是现代视觉百科全书与精英铁路基础设施实地指南和高端编辑信息图系统的结合。\\n- 1:1 方形构图 \\\\- 深色高级城市科技背景，带有微妙的铁路示意图、地铁地图和未来蓝图叠加 \\\\- 优雅的调色板，使用深海军蓝、哑光黑、钢灰、电蓝色点缀和柔和的白色灯光 \\\\- 精致的编辑排版层次，具有现代交通美学 \\\\- 圆角模块化信息卡片，间距清晰 \\\\- 温和的现实反射和高级HUD风格的分隔符 \\\\- 最小化的交通系统图标 \\\\- 极其详细的中央地铁列车渲染，以戏剧性的四分之三视角展示在未来的地下车站中 \\\\- 细腻的精准注释线，指向交通系统和智能工程特性 \\\\- 清晰有序的“知识优先”布局，信息密度高但间距舒适 \\\\- 主题展示：\\\\ 一个令人惊叹的超详细现实渲染的{METRO_NAME}现代地铁列车位于中心，具有流线型的列车设计、发光的目的地显示屏、逼真的不锈钢纹理、照明站台灯光、智能玻璃窗户、高级城市环境真实感和未来铁路基础设施。 \\\\- 在地铁周围添加科学和工程标注，解释：再生制动系统、智能信号和CBTC控制、电动推进系统、乘客信息系统、安全和监控技术、站台屏蔽门、节能设计、智能通风系统、无障碍功能、轨道和基础设施工程。 \\\\- 包括模块化的信息图表部分，如：地铁系统概述、技术规格、列车尺寸和布局、乘客容量和流动、智能控制系统、可持续性特点、轨道和基础设施工程、信号和自动化、车站设计和设施、安全和应急系统、乘客体验特点、城市连接和网络地图、能效比较、建设与扩展时间表、“五大智能创新”部分、为未来智慧城市打造。 \\\\- 添加小型高级可视化模块，如：地铁网络地图、列车蓝图图解、车站布局图形、乘客流动可视化、信号工作流程图、能效比较图表、列车配置插图、智慧城市连接图形、站台安全图、基础设施截面视图。 \\\\- 风格关键词：“高级城市移动百科全书”、“编辑地铁工程手册”、“高端交通信息图”、“科学铁路基础设施海报”、“博物馆级交通参考页”、“模块化智慧城市知识系统”、“清洁交通编辑设计”、“超详细地铁可视化”。 \\\\- 避免：杂乱的公共广告美学、卡通交通风格、不切实际的科幻悬浮列车、过度的赛博朋克霓虹灯、混乱的城市场景、通用的地铁海报布局。 \\\\- 最终结果应该类似于为交通爱好者、建筑师、工程师、城市规划师、交通设计师和教育基础设施档案馆创建的专业出版的铁路基础设施参考书页。",
  "tags": [],
  "related_templates": [],
  "published_at": "2026-07-23"
}