{
  "slug": "freestylefly-423",
  "title": "这条 prompt 详细描述了一个充满秋日氛围的时尚场景，适合用于高端服装品牌的营销宣传或时尚杂志封面设计，能够传达出品牌优雅、高品质的形象。",
  "scene": "cross-border",
  "industry": "other",
  "style": "minimal",
  "image_url": "/assets/freestylefly-423/v1.webp",
  "image_alt": "这条 prompt 详细描述了一个充满秋日氛围的时尚场景，适合用于高端服装品牌的营销宣传或时尚杂志封面设计，能够传达出品牌优雅、高品质的形象。",
  "prompt_original": "Full-body fashion illustration of a young woman walking down a Parisian street in autumn, wearing a long camel wool coat draped open over a black ribbed turtleneck sweater and high-waisted wide-leg cream trousers, holding a quilted tan leather shoulder bag with interlocking CC logo and chain strap in her left hand while her right hand slides into a pocket, short dark brown wavy hair gently lifted by a breeze, pearl stud earrings, natural fresh makeup and a confident serene expression; cinematic shallow depth of field with soft warm golden-hour light, subtle bokeh on Haussmann-style buildings and slow-moving cars in the blurred background, scattered fallen leaves on the pavement; semi-realistic digital painting / fashion illustration style with clean linework, soft gradients, high-detail fabric textures and realistic folds, emphasis on elegant silhouettes and tactile materials, muted autumn palette (camel, cream, black, warm ochre), vertical composition, crisp foreground, gentle film grain and polished finishing.",
  "prompt_zh": "全身时尚插画，描绘一位年轻女性在秋季的巴黎街道上行走，穿着一件敞开的长款驼色羊毛大衣，内搭黑色罗纹高领毛衣和高腰宽腿奶油色长裤，左手提着一个带有互扣CC标志和链条肩带的绗缝棕色皮包，右手插在口袋里，短而深棕色的波浪发被微风轻轻吹起，佩戴珍珠耳钉，妆容自然清新，表情自信宁静；电影般的浅景深效果，温暖的金色光线，背景中的奥斯曼风格建筑和缓慢行驶的汽车有轻微的散景效果，人行道上有零星的落叶；半写实的数字绘画/时尚插画风格，线条清晰，柔和的渐变，高细节的织物质感和真实的褶皱，强调优雅的轮廓和触感材料，使用秋日色调（驼色、奶油色、黑色、暖赭色），竖向构图，前景清晰，轻微的胶片颗粒感和精致的完成度。",
  "tags": [],
  "related_templates": [],
  "published_at": "2026-07-23"
}