{
  "slug": "freestylefly-185",
  "title": "这条 prompt 详细描述了角色的外观、服装和背景，非常适合用于制作动漫主题的手机壁纸或宣传素材，能够吸引喜欢二次元文化的年轻用户。",
  "scene": "cross-border",
  "industry": "other",
  "style": "minimal",
  "image_url": "/assets/freestylefly-185/v1.webp",
  "image_alt": "这条 prompt 详细描述了角色的外观、服装和背景，非常适合用于制作动漫主题的手机壁纸或宣传素材，能够吸引喜欢二次元文化的年轻用户。",
  "prompt_original": "[中文]\r\n生成一张高质量二次元美少女图片。 \r\n\r\n 角色设定：\r\n\r\n- 年龄：17岁 \r\n- 发型：双马尾，颜色：樱花粉，发梢带点渐变紫色\r\n - 眼睛：大而明亮，紫色瞳孔，有星星高光\r\n - 服装：JK制服，白色衬衫，深蓝色格子裙，红色领结\r\n - 配饰：白色过膝袜，棕色小皮鞋，头上戴一个粉色蝴蝶结  \r\n\r\n风格要求：\r\n - 日系动画风格，线条清晰 - 色彩鲜艳，对比度高 - 光影柔和，有层次感 \r\n- 背景：樱花树下，花瓣飘落，远处是学校教学楼  表情：微笑，有点害羞 姿势：站姿，双手放在身后，身体微微前倾  \r\n\r\n比例：16:9（手机壁纸） 质量：8K，超精细，细节丰富\r\n\r\n[English]\r\nGenerate a high-quality anime beautiful girl image. \r\n\r\n Character setting:\r\n\r\n- Age: 17 years old\r\n- Hairstyle: twin tails, color: cherry blossom pink, hair tips with a bit of gradient purple\r\n - Eyes: large and bright, purple pupils, with star highlights\r\n - Clothing: JK uniform, white shirt, dark blue plaid skirt, red bow tie\r\n - Accessories: white over-the-knee socks, brown leather shoes, wearing a pink bow on the head  \r\n\r\n Style requirements:\r\n - Japanese animation style, clear lines - bright colors, high contrast - soft light and shadow, with a sense of layering \r\n- Background: under the cherry blossom tree, petals falling, school teaching building in the distance  Expression: smiling, a bit shy Pose: standing posture, hands placed behind the back, body slightly leaning forward  \r\n\r\nProportion: 16:9 (mobile wallpaper) Quality: 8K, ultra-fine, rich in details",
  "prompt_zh": "生成一张高质量二次元美少女图片。角色设定：- 年龄：17岁 - 发型：双马尾，颜色：樱花粉，发梢带点渐变紫色 - 眼睛：大而明亮，紫色瞳孔，有星星高光 - 服装：JK制服，白色衬衫，深蓝色格子裙，红色领结 - 配饰：白色过膝袜，棕色小皮鞋，头上戴一个粉色蝴蝶结。风格要求：- 日系动画风格，线条清晰 - 色彩鲜艳，对比度高 - 光影柔和，有层次感 - 背景：樱花树下，花瓣飘落，远处是学校教学楼。表情：微笑，有点害羞。姿势：站姿，双手放在身后，身体微微前倾。比例：16:9（手机壁纸）。质量：8K，超精细，细节丰富。",
  "tags": [],
  "related_templates": [],
  "published_at": "2026-07-23"
}